{
"title": "ذم الحمق و السفه",
"type": "text",
"data": [
{
"text": "الْحُمْقُ شَقَاءٌ",
"source": "غرر الحكم ودرر الكلم"
},
{
"text": "الْحُمْقُ أَضَرُّ الْأَصْحَابِ",
"source": "غرر الحكم ودرر الكلم"
},
{
"text": "الْحُمْقُ أَدْوَأُ الدَّاءِ",
"source": "غرر الحكم ودرر الكلم"
},
{
"text": "الْحُمْقُ مِنْ ثِمَارِ الْجَهْلِ",
"source": "غرر الحكم ودرر الكلم"
},
{
"text": "الْحُمْقُ دَاءٌ لَا يُدَاوَى وَمَرَضٌ لَا يَبْرَأُ",
"source": "غرر الحكم ودرر الكلم"
},
{
"text": "أَفْقَرُ الْفَقْرِ الْحُمْقُ",
"source": "غرر الحكم ودرر الكلم"
},
{
"text": "أَضَرُّ شَيْ‏ءٍ الْحُمْقُ",
"source": "غرر الحكم ودرر الكلم"
},
{
"text": "بِئْسَ الدَّاءُ الْحُمْقُ",
"source": "غرر الحكم ودرر الكلم"
},
{
"text": "فَقْرُ الْحُمْقِ [الْأَحْمَقِ‏] لَا يُغْنِيهِ الْمَالُ",
"source": "غرر الحكم ودرر الكلم"
},
{
"text": "كُلُّ فَقْرٍ يُسَدُّ إِلَّا فَقْرَ الْحُمْقِ",
"source": "غرر الحكم ودرر الكلم"
},
{
"text": "لَا فَاقَةَ أَشَدُّ مِنَ الْحُمْقِ",
"source": "غرر الحكم ودرر الكلم"
},
{
"text": "لَا دَاءَ أَدْوَى مِنَ الْحُمْقِ",
"source": "غرر الحكم ودرر الكلم"
},
{
"text": "السَّفَهُ خُرْقٌ",
"source": "غرر الحكم ودرر الكلم"
},
{
"text": "سِلَاحُ الْجَهْلِ السَّفَهُ",
"source": "غرر الحكم ودرر الكلم"
},
{
"text": "لَيْسَ السَّفَهُ كَالْحِلْمِ",
"source": "غرر الحكم ودرر الكلم"
},
{
"text": "لَا يَعْرِفُ السَّفِيهُ حَقَّ الْحَلِيمِ",
"source": "غرر الحكم ودرر الكلم"
},
{
"text": "الْخُرْقُ [الخلق‏] شَرُّ خُلُقٍ",
"source": "غرر الحكم ودرر الكلم"
},
{
"text": "الْخُرْقُ [الْحُزْنُ‏] شَيْنُ الْخُلُقِ",
"source": "غرر الحكم ودرر الكلم"
},
{
"text": "مَا كَانَ الْخُرْقُ فِي شَيْ‏ءٍ إِلَّا شَانَهُ",
"source": "غرر الحكم ودرر الكلم"
},
{
"text": "لَا خُلَّةَ أَزْرَى مِنَ الْخُرْقِ",
"source": "غرر الحكم ودرر الكلم"
},
{
"text": "مِنْ أَقْبَحِ الشِّيَمِ الْغَبَاوَةُ",
"source": "غرر الحكم ودرر الكلم"
}
]
}