{
"title": "ما يوجب الهداية",
"type": "text",
"data": [
{
"text": "هُدِيَ [هَدَى اللَّهُ‏] مَنِ ادَّرَعَ لِبَاسَ الصَّبْرِ وَالْيَقِينِ",
"source": "غرر الحكم ودرر الكلم"
},
{
"text": "هُدِيَ مَنْ تَجَلْبَبَ جِلْبَابَ الدِّينِ",
"source": "غرر الحكم ودرر الكلم"
},
{
"text": "هُدِيَ [هَدَى اللَّهُ‏] مَنْ حَسُنَ إِسْلَامُهُ",
"source": "غرر الحكم ودرر الكلم"
},
{
"text": "هُدِيَ مَنْ سَلَّمَ مَقَادَتَهُ إِلَى اللَّهِ وَرَسُولِهِ وَوَلِيِّ أَمْرِهِ",
"source": "غرر الحكم ودرر الكلم"
},
{
"text": "هُدِيَ مَنْ أَخْلَصَ إِيمَانَهُ",
"source": "غرر الحكم ودرر الكلم"
},
{
"text": "هُدِيَ مَنْ أَطَاعَ رَبَّهُ وَخَافَ ذَنْبَهُ",
"source": "غرر الحكم ودرر الكلم"
},
{
"text": "إِذَا أَنْتَ هَدَيْتَ لِقَصْدِكَ فَكُنْ أَخْشَعَ مَا تَكُونُ لِرَبِّكَ",
"source": "غرر الحكم ودرر الكلم"
},
{
"text": "رَحِمَ اللَّهُ عَبْداً سَمِعَ حُكْماً فَوَعَى وَدُعِيَ [فَدُعِيَ‏] إِلَى رَشَادٍ فَدَنَى وَأَخَذَ بِحُجْزَةِ هَادٍ فَنَجَا",
"source": "غرر الحكم ودرر الكلم"
},
{
"text": "طُوبَى لِمَنْ سَلَكَ طَرِيقَ السَّلَامَةِ بِبَصَرِ مَنْ بَصَّرَهُ وَطَاعَةِ هَادٍ أَمَرَهُ",
"source": "غرر الحكم ودرر الكلم"
},
{
"text": "فَازَ مَنِ اسْتَصْبَحَ بِنُورِ الْهُدَى وَخَالَفَ دَوَاعِيَ الْهَوَى وَجَعَلَ [جمل‏] الْإِيمَانَ عُدَّةَ مَعَادِهِ وَالتَّقْوَى ذُخْرَهُ وَزَادَهُ",
"source": "غرر الحكم ودرر الكلم"
},
{
"text": "قَدْ دُلِلْتُمْ إِنِ اسْتَدْلَلْتُمْ وَوُعِظْتُمْ إِنِ اتَّعَظْتُمْ وَنُصِحْتُمْ إِنِ انْتَصَحْتُمْ",
"source": "غرر الحكم ودرر الكلم"
},
{
"text": "كَفَاكَ مِنْ عَقْلِكَ مَا أَبَانَ لَكَ رُشْدَكَ مِنْ غَيِّكَ",
"source": "غرر الحكم ودرر الكلم"
},
{
"text": "لَقَدْ بُصِّرْتُمْ إِنْ أَبْصَرْتُمْ وَأُسْمِعْتُمْ إِنْ سَمِعْتُمْ وَهُدِيتُمْ إِنِ اهْتَدَيْتُمْ",
"source": "غرر الحكم ودرر الكلم"
},
{
"text": "لَقَدْ جَاهَرَتْكُمُ الْعِبَرُ وَزَجَرَكُمْ مَا فِيهِ مُزْدَجَرٌ وَمَا بَلَّغَ عَنِ اللَّهِ بَعْدَ رَسُولِ اللَّهِ مِثْلُ النُّذُرِ",
"source": "غرر الحكم ودرر الكلم"
},
{
"text": "يَعْطِفُ الْهَوَى عَلَى الْهُدَى إِذَا عَطَفُوا الْهُدَى عَلَى الْهَوَى وَيَعْطِفُ الرَّأْيَ عَلَى الْقُرْآنِ إِذَا عَطَفُوا الْقُرْآنَ عَلَى الرَّأْيِ",
"source": "غرر الحكم ودرر الكلم"
}
]
}