{
"title": "الدنيا دار فناء",
"type": "text",
"data": [
{
"text": "الدُّنْيَا فَانِيَةٌ",
"source": "غرر الحكم ودرر الكلم"
},
{
"text": "الْعَيْشُ يَحْلُو وَيَمُرُّ",
"source": "غرر الحكم ودرر الكلم"
},
{
"text": "الدُّنْيَا كَيَوْمٍ مَضَى وَشَهْرٍ انْقَضَى",
"source": "غرر الحكم ودرر الكلم"
},
{
"text": "الدُّنْيَا مُنْتَقِلَةٌ فَانِيَةٌ إِنْ بَقِيَتْ لَكَ لَمْ تَبْقَ لَهَا",
"source": "غرر الحكم ودرر الكلم"
},
{
"text": "أَوْقَاتُ الدُّنْيَا وَإِنْ طَالَتْ قَصِيرَةٌ وَالْمُتْعَةُ بِهَا وَإِنْ كَثُرَتْ يَسِيرَةٌ",
"source": "غرر الحكم ودرر الكلم"
},
{
"text": "أَقْبِلُوا عَلَى مَنْ أَقْبَلَتْ عَلَيْهِ الدُّنْيَا فَإِنَّهُ أَجْدَرُ بِالْغِنَى",
"source": "غرر الحكم ودرر الكلم"
},
{
"text": "إِنَّ لِلَّهِ سُبْحَانَهُ مَلَكاً يُنَادِي فِي كُلِّ يَوْمٍ يَا أَهْلَ الدُّنْيَا لِدُوا لِلْمَوْتِ وَابْنُوا لِلْخَرَابِ وَاجْمَعُوا لِلذَّهَابِ",
"source": "غرر الحكم ودرر الكلم"
},
{
"text": "إِنَّمَا خُلِقْتُمْ لِلْبَقَاءِ لَا لِلْفَنَاءِ وَإِنَّكُمْ فِي دَارِ بُلْغَةٍ وَمَنْزِلِ قُلْعَةٍ",
"source": "غرر الحكم ودرر الكلم"
},
{
"text": "إِذَا كَانَ الْبَقَاءُ لَا يُوجَدُ فَالنَّعِيمُ زَائِلٌ",
"source": "غرر الحكم ودرر الكلم"
},
{
"text": "بِئْسَ الِاخْتِيَارُ التَّعَوُّضُ [التَّعْوِيضُ‏] بِمَا يَفْنَى عَمَّا يَبْقَى",
"source": "غرر الحكم ودرر الكلم"
},
{
"text": "بَقَاؤُكُمْ إِلَى فَنَاءٍ وَفَنَاؤُكُمْ إِلَى بَقَاءٍ",
"source": "غرر الحكم ودرر الكلم"
},
{
"text": "تَمِيزُ الْبَاقِي مِنَ الْفَانِي مِنْ أَشْرَفِ النَّظَرِ",
"source": "غرر الحكم ودرر الكلم"
},
{
"text": "ظَلَمَ نَفْسَهُ مَنْ رَضِيَ بِدَارِ الْفَنَاءِ عِوَضاً عَنْ دَارِ الْبَقَاءِ",
"source": "غرر الحكم ودرر الكلم"
},
{
"text": "غَايَةُ الدُّنْيَا الْفَنَاءُ",
"source": "غرر الحكم ودرر الكلم"
},
{
"text": "غَرَّارَةٌ غَرُورٌ مَا فِيهَا فَانِيَةٌ فَانٍ مَنْ عَلَيْهَا",
"source": "غرر الحكم ودرر الكلم"
},
{
"text": "كُلُّ جَمْعٍ إِلَى شَتَاتٍ",
"source": "غرر الحكم ودرر الكلم"
},
{
"text": "كُلُّ مُدَّةٍ مِنَ الدُّنْيَا إِلَى انْتِهَاءٍ وَكُلُّ حَيٍّ فِيهَا إِلَى مَمَاتٍ وَفَنَاءٍ",
"source": "غرر الحكم ودرر الكلم"
},
{
"text": "كَمْ مِنْ بَانٍ مَا لَا يَسْكُنُهُ",
"source": "غرر الحكم ودرر الكلم"
},
{
"text": "كُرُورُ الْأَيَّامِ أَحْلَامٌ وَلَذَّاتُهَا آلَامٌ وَمَوَاهِبُهَا فَنَاءٌ وَأَسْقَامٌ",
"source": "غرر الحكم ودرر الكلم"
},
{
"text": "لِكُلِّ شَيْ‏ءٍ فَوْتٌ",
"source": "غرر الحكم ودرر الكلم"
},
{
"text": "لِكُلِّ شَيْ‏ءٍ مِنَ الدُّنْيَا انْقِضَاءٌ وَفَنَاءٌ",
"source": "غرر الحكم ودرر الكلم"
},
{
"text": "مَنْ أَغْبَنُ مِمَّنْ بَاعَ الْبَقَاءَ بِالْفَنَاءِ",
"source": "غرر الحكم ودرر الكلم"
},
{
"text": "مَا خَيْرُ دَارٍ تَنْقُضُ نَقْضَ الْبِنَاءِ وَعُمُرٍ يَفْنَى فَنَاءَ الزَّادِ",
"source": "غرر الحكم ودرر الكلم"
},
{
"text": "مَا أَقْرَبَ الدُّنْيَا مِنَ الذَّهَابِ وَالشَّيْبَ مِنَ الشَّبَابِ وَالشَّكَّ مِنَ الِارْتِيَابِ",
"source": "غرر الحكم ودرر الكلم"
},
{
"text": "مَا وَلَدْتُمْ فَلِلتُّرَابِ وَمَا بَنَيْتُمْ فَلِلْخَرَابِ وَمَا جَمَعْتُمْ فَلِلذَّهَابِ وَمَا عَمِلْتُمْ فَفِي كِتَابٍ مُدَّخَرٌ لِيَوْمِ الْحِسَابِ",
"source": "غرر الحكم ودرر الكلم"
},
{
"text": "نَحْنُ أَعْوَانُ الْمَنُونِ وَأَنْفُسُنَا نَصْبُ الْحُتُوفِ فَمِنْ أَيْنَ نَرْجُو الْبَقَاءَ وَهَذَا اللَّيْلُ وَالنَّهَارُ لَمْ يَرْفَعَا مِنْ شَيْ‏ءٍ شَرَفاً إِلَّا أَسْرَعَا الْكَرَّةَ فِي هَدْمِ مَا بَنَيَا وَتَفْرِيقِ مَا جَمَعَا",
"source": "غرر الحكم ودرر الكلم"
},
{
"text": "هَلْ يَنْتَظِرُ أَهْلُ مُدَّةِ الْبَقَاءِ إِلَّا آوِنَةَ الْفَنَاءِ مَعَ قُرْبِ الزَّوَالِ وَأُزُوفِ الِانْتِقَالِ",
"source": "غرر الحكم ودرر الكلم"
},
{
"text": "لَا تَرْغَبْ فِي كُلِّ مَا يَفْنَى وَيَذْهَبُ فَكَفَى بِذَلِكَ مَضَرَّةً",
"source": "غرر الحكم ودرر الكلم"
},
{
"text": "كُلُّ فَانٍ يَسِيرٌ",
"source": "غرر الحكم ودرر الكلم"
}
]
}