{
"title": "أهمية الذكر و بعض آثاره",
"type": "text",
"data": [
{
"text": "أَهْلُ الذِّكْرِ أَهْلُ اللَّهِ وَخَاصَّتُهُ",
"source": "غرر الحكم ودرر الكلم"
},
{
"text": "الذِّكْرُ أَفْضَلُ الْغَنِيمَتَيْنِ",
"source": "غرر الحكم ودرر الكلم"
},
{
"text": "الذِّكْرُ لَيْسَ مِنْ مَرَاسِمِ اللِّسَانِ وَلَا مِنْ مَنَاسِمِ الْفِكْرِ وَلَكِنَّهُ أَوَّلٌ مِنَ الْمَذْكُورِ وَثَانٍ مِنَ الذَّاكِرِ",
"source": "غرر الحكم ودرر الكلم"
},
{
"text": "الْجُلُوسُ فِي الْمَسْجِدِ مِنْ بَعْدِ طُلُوعِ الْفَجْرِ إِلَى حِينِ طُلُوعِ الشَّمْسِ لِلِاشْتِغَالِ بِذِكْرِ اللَّهِ سُبْحَانَهُ أَسْرَعُ فِي تَيْسِيرِ الرِّزْقِ مِنَ الضَّرْبِ فِي أَقْطَارِ الْأَرْضِ",
"source": "غرر الحكم ودرر الكلم"
},
{
"text": "اذْكُرْ عِنْدَ الظُّلْمِ عَدْلَ اللَّهِ فِيكَ وَعِنْدَ الْقُدْرَةِ قُدْرَةَ اللَّهِ عَلَيْكَ",
"source": "غرر الحكم ودرر الكلم"
},
{
"text": "اشْحَنِ الْخَلْوَةَ بِالذِّكْرِ وَاصْحَبِ النِّعَمَ بِالشُّكْرِ",
"source": "غرر الحكم ودرر الكلم"
},
{
"text": "أَفِيضُوا فِي ذِكْرِ اللَّهِ فَإِنَّهُ أَحْسَنُ الذِّكْرِ",
"source": "غرر الحكم ودرر الكلم"
},
{
"text": "أَصْلُ صَلَاحِ الْقَلْبِ اشْتِغَالُهُ بِذِكْرِ اللَّهِ",
"source": "غرر الحكم ودرر الكلم"
},
{
"text": "إِنَّ أَوْلِيَاءَ اللَّهِ لَأَكْثَرُ النَّاسِ لَهُ ذِكْراً وَأَدْوَمُهُمْ لَهُ شُكْراً وَأَعْظَمُهُمْ عَلَى بَلَائِهِ صَبْراً",
"source": "غرر الحكم ودرر الكلم"
},
{
"text": "إِنَّ لِلذِّكْرِ أَهْلًا أَخَذُوهُ مِنَ الدُّنْيَا بَدَلًا فَلَمْ تَشْغَلْهُمْ تِجَارَةٌ وَلَا بَيْعٌ عَنْ ذِكْرٍ يَقْطَعُونَ بِهِ أَيَّامَ الْحَيَاةِ وَيَهْتِفُونَ بِهِ فِي آذَانِ الْغَافِلِينَ",
"source": "غرر الحكم ودرر الكلم"
},
{
"text": "إِذَا رَأَيْتَ اللَّهَ سُبْحَانَهُ يُؤْنِسُكَ بِذِكْرِهِ فَقَدْ أَحَبَّكَ",
"source": "غرر الحكم ودرر الكلم"
},
{
"text": "بِذِكْرِ اللَّهِ تُسْتَنْزَلُ الرَّحْمَةُ",
"source": "غرر الحكم ودرر الكلم"
},
{
"text": "خَيْرُ مَا اسْتُنْجِحَتْ بِهِ الْأُمُورُ ذِكْرُ اللَّهِ سُبْحَانَهُ",
"source": "غرر الحكم ودرر الكلم"
},
{
"text": "ذِكْرُ اللَّهِ مَطْرَدَةُ الشَّيْطَانِ",
"source": "غرر الحكم ودرر الكلم"
},
{
"text": "ذِكْرُ اللَّهِ شِيمَةُ الْمُتَّقِينَ",
"source": "غرر الحكم ودرر الكلم"
},
{
"text": "ذَاكِرُ اللَّهِ مِنَ الْفَائِزِينَ",
"source": "غرر الحكم ودرر الكلم"
},
{
"text": "ذِكْرُ اللَّهِ سَجِيَّةُ كُلِّ مُحْسِنٍ وَشِيمَةُ كُلِّ مُؤْمِنٍ",
"source": "غرر الحكم ودرر الكلم"
},
{
"text": "ذِكْرُ اللَّهِ طَارِدُ اللَّأْوَاءِ وَالْبُؤْسِ",
"source": "غرر الحكم ودرر الكلم"
},
{
"text": "ذِكْرُ اللَّهِ دَوَاءُ أَعْلَالِ النُّفُوسِ",
"source": "غرر الحكم ودرر الكلم"
},
{
"text": "ذِكْرُ اللَّهِ دِعَامَةُ الْإِيمَانِ وَعِصْمَةٌ مِنَ الشَّيْطَانِ",
"source": "غرر الحكم ودرر الكلم"
},
{
"text": "ذِكْرُ اللَّهِ رَأْسُ مَالِ كُلِّ مُؤْمِنٍ وَرِبْحُهُ السَّلَامَةُ مِنَ الشَّيْطَانِ",
"source": "غرر الحكم ودرر الكلم"
},
{
"text": "سَامِعُ ذِكْرِ اللَّهِ ذَاكِرٌ",
"source": "غرر الحكم ودرر الكلم"
},
{
"text": "طُوبَى لِمَنْ صَمَتَ إِلَّا مِنْ ذِكْرِ اللَّهِ",
"source": "غرر الحكم ودرر الكلم"
},
{
"text": "عَوِّدْ نَفْسَكَ الِاسْتِهْتَارَ [عدم الاستهتار] بِالذِّكْرِ وَالِاسْتِغْفَارِ فَإِنَّهُ يَمْحُو عَنْكَ الْحَوْبَةَ وَيُعَظِّمُ لَكَ الْمَثُوبَةَ",
"source": "غرر الحكم ودرر الكلم"
},
{
"text": "كُنْ فِي الْمَلَإِ وَقُوراً وَكُنْ فِي الْخَلَاءِ ذَكُوراً",
"source": "غرر الحكم ودرر الكلم"
},
{
"text": "مَنْ ذَكَرَ اللَّهَ ذَكَرَهُ",
"source": "غرر الحكم ودرر الكلم"
},
{
"text": "مَنِ اشْتَغَلَ بِذِكْرِ اللَّهِ طَيَّبَ اللَّهُ ذِكْرَهُ",
"source": "غرر الحكم ودرر الكلم"
},
{
"text": "لَا تَذْكُرِ اللَّهَ سُبْحَانَهُ سَاهِياً وَلَا تَنْسَهُ لَاهِياً وَ اذْكُرْهُ [ذِكْراً] كَامِلًا يُوَافِقُ فِيهِ قَلْبُكَ لِسَانَكَ وَيُطَابِقُ إِضْمَارُكَ إِعْلَانَكَ وَلَنْ تَذْكُرَهُ حَقِيقَةَ الذِّكْرِ حَتَّى تَنْسَى نَفْسَكَ فِي ذِكْرِكَ وَتَفْقُدَهَا فِي أَمْرِكَ",
"source": "غرر الحكم ودرر الكلم"
}
]
}