{
"title": "دستورات طبية",
"type": "text",
"data": [
{
"text": "الْمَرَضُ حَبْسُ الْبَدَنِ",
"source": "غرر الحكم ودرر الكلم"
},
{
"text": "اللَّبَنُ أَحَدُ اللَّحْمَيْنِ",
"source": "غرر الحكم ودرر الكلم"
},
{
"text": "الْمَرَضُ أَحَدُ الْحَبْسَيْنِ",
"source": "غرر الحكم ودرر الكلم"
},
{
"text": "رُبَّ دَوَاءٍ جَلَبَ دَاءً",
"source": "غرر الحكم ودرر الكلم"
},
{
"text": "رُبَّ دَاءٍ انْقَلَبَ دَوَاءً",
"source": "غرر الحكم ودرر الكلم"
},
{
"text": "رُبَّمَا كَانَ الدَّاءُ شِفَاءً",
"source": "غرر الحكم ودرر الكلم"
},
{
"text": "رُبَّمَا كَانَ الدَّوَاءُ دَاءً",
"source": "غرر الحكم ودرر الكلم"
},
{
"text": "قَلَّ مَنْ أَكْثَرَ مِنْ فُضُولِ الطَّعَامِ إِلَّا لَزِمَتْهُ الْأَسْقَامُ",
"source": "غرر الحكم ودرر الكلم"
},
{
"text": "كَمْ مِنْ أَكْلَةٍ مَنَعَتْ [ضَيَّعَتْ‏] أَكَلَاتٍ",
"source": "غرر الحكم ودرر الكلم"
},
{
"text": "كُلُوا الْأُتْرُجَّ قَبْلَ الطَّعَامِ وَبَعْدَهُ فَآلُ مُحَمَّدٍ يَفْعَلُونَ ذَلِكَ",
"source": "غرر الحكم ودرر الكلم"
},
{
"text": "لِكُلِّ عِلَّةٍ دَوَاءٌ",
"source": "غرر الحكم ودرر الكلم"
},
{
"text": "لِكُلِّ حَيٍّ دَاءٌ",
"source": "غرر الحكم ودرر الكلم"
},
{
"text": "مَنْ كَثُرَتْ أَدْوَاؤُهُ لَمْ يُعْرَفْ شِفَاؤُهُ",
"source": "غرر الحكم ودرر الكلم"
},
{
"text": "مَنْ كَتَمَ الْأَطِبَّاءَ مَرَضَهُ خَانَ بَدَنَهُ",
"source": "غرر الحكم ودرر الكلم"
},
{
"text": "مَنْ كَتَمَ مَكْنُونَ دَائِهِ عَجَزَ طَبِيبُهُ عَنْ شِفَائِهِ",
"source": "غرر الحكم ودرر الكلم"
},
{
"text": "مَنْ غَرَسَ فِي نَفْسِهِ مَحَبَّةَ أَنْوَاعِ الطَّعَامِ اجْتَنَى ثِمَارَ فُنُونِ الْأَسْقَامِ",
"source": "غرر الحكم ودرر الكلم"
},
{
"text": "مَنْ لَمْ يَحْتَمِلْ مَرَارَةَ الدَّوَاءِ دَامَ أَلَمُهُ",
"source": "غرر الحكم ودرر الكلم"
}
]
}