{
"title": "باللّفظ المطلق وهو إحدى وخمسون حكمة",
"type": "text",
"data": [
{
"text": "رِضَا اللهِ سُبْحانهُ مَقْرُونٌ بِطاعَتِه.",
"source": "عيون الحكم والمواعظ"
},
{
"text": "رِزْقُكَ يَطْلبُكَ فَأرِحْ نَفْسَكَ مِنْ طَلَبِه.",
"source": "عيون الحكم والمواعظ"
},
{
"text": "رِضَا اللهِ سُبْحانَهُ أَقْرَبُ غايَةٍ تُدْرَكُ.",
"source": "عيون الحكم والمواعظ"
},
{
"text": "رِضَا الْمُتَجَنِّي غايَةٌ لا تُدْرَكُ.",
"source": "عيون الحكم والمواعظ"
},
{
"text": "رِضاكَ عَنْ نَفْسِكَ مِنْ فَسادِ عَقْلِكَ.",
"source": "عيون الحكم والمواعظ"
},
{
"text": "رِضاكَ بِالدُّنْيا مِنْ |سوءِ اخْتِيارِكَ وَ| شَقاءِ جَدِّكَ.",
"source": "عيون الحكم والمواعظ"
},
{
"text": "رُكُوبُ الْأَهْوالِ يَكْسِبُ الْأَمْوالَ.",
"source": "عيون الحكم والمواعظ"
},
{
"text": "رُكُوبُ الْأَطْماعِ يَقْطَعُ قُلُوبَ الرِّجالِ.",
"source": "عيون الحكم والمواعظ"
},
{
"text": "رَأْيُ الْعاقِلِ يُنْجي.",
"source": "عيون الحكم والمواعظ"
},
{
"text": "رَأْيُ الْجاهِلِ يُرْدي.",
"source": "عيون الحكم والمواعظ"
},
{
"text": "رِزْقُ الرَّجُلِ عَلى قَدْرِ نِيَّتِه.",
"source": "عيون الحكم والمواعظ"
},
{
"text": "رَأْيُ الرَّجُلِ عَلى قَدْرِ تَجْرِبَتِه.",
"source": "عيون الحكم والمواعظ"
},
{
"text": "رِفْقُ الْمَرْءِ |وَ سَخاءُ هُ يُحَبِّبُهُ إِلى أَعْدائِه.",
"source": "عيون الحكم والمواعظ"
},
{
"text": "رُتْبَةُ الْعِلْمِ أَعْلى الْمَراتِبِ.",
"source": "عيون الحكم والمواعظ"
},
{
"text": "راقِبِ الْعَواقِبَ تَنْجُ مِنَ الْمَعاطِبِ.",
"source": "عيون الحكم والمواعظ"
},
{
"text": "رَسُولُكَ تَرْجُمانُ عَقْلِكَ وَ احْتِمالُكَ دَليلُ حِلْمِكَ.",
"source": "عيون الحكم والمواعظ"
},
{
"text": "رَسُولُكَ ميزانُ نَبْلِكَ وَ قَلَمُكَ أَبْلَغُ مَنْ يَنْطِقُ عَنْكَ.",
"source": "عيون الحكم والمواعظ"
},
{
"text": "رَغْبَتُكَ في زاهِدٍ فيكَ ذُلٌّ.",
"source": "عيون الحكم والمواعظ"
},
{
"text": "رَغْبَتُكَ فِي الْمُسْتَحيلِ جَهْلٌ.",
"source": "عيون الحكم والمواعظ"
},
{
"text": "راكِبُ اللَّجاجِ مُتَعَرِّضٌ لِلبَلاءِ.",
"source": "عيون الحكم والمواعظ"
},
{
"text": "راكِبُ الظُّلْم يَكْبُو بِه مَراكَبُهُ.",
"source": "عيون الحكم والمواعظ"
},
{
"text": "راكِبُ الْعُنْفِ يَتَعَذَّرُ عَلَيْهِ مَطْلَبُهُ.",
"source": "عيون الحكم والمواعظ"
},
{
"text": "رَدْعُ النَّفْسِ عَنِ الْهَوَى |هو الْجِهادُ الْأَكبَرُ النّافِعُ.",
"source": "عيون الحكم والمواعظ"
},
{
"text": "رَدْعُ الْحِرْصِ مَنْعُ الشَّرَهِ وَ الْمَطامِعِ.",
"source": "عيون الحكم والمواعظ"
},
{
"text": "رَدُّ الْغَضَبِ بِالْحِلمِ ثَمَرَةُ الْعَقْلِ.",
"source": "عيون الحكم والمواعظ"
},
{
"text": "رَوِّ قَبْلَ الْفِعْلِ كَيلا تُعابَ بِما تَفْعَلُ.",
"source": "عيون الحكم والمواعظ"
},
{
"text": "رَوِيَّةُ الْمُتأَنِّي أَفْضَلُ مِنْ بَديهَةِ الْعَجِلِ.",
"source": "عيون الحكم والمواعظ"
},
{
"text": "روحوا فِي الْمَكارِمِ وَ أَدْلِجُوا في حاجَةٍ مَنْ هُوَ نائِمٌ.",
"source": "عيون الحكم والمواعظ"
},
{
"text": "رَدْعُ النَّفْسِ عَنِ |زَخارِفِ الدُّنْيا ثَمَرةُ الْعقْلِ.",
"source": "عيون الحكم والمواعظ"
},
{
"text": "رَدْعُ الْهَوى شيمَةُ الْعُقَلاءِ.",
"source": "عيون الحكم والمواعظ"
},
{
"text": "رَدْعُ الشَّهْوَةِ وَ الْغَضَبِ جِهادُ النُّبَلاءِ.",
"source": "عيون الحكم والمواعظ"
},
{
"text": "رُدُّوا الْبادِرَةَ بِالْحِلمِ.",
"source": "عيون الحكم والمواعظ"
},
{
"text": "رُدُّوا الْجَهْلَ بِالْعِلمِ.",
"source": "عيون الحكم والمواعظ"
},
{
"text": "رُدَّ نَفْسَكَ عَنِ الشَّهَواتِ وَ أَقِمْها عَلى كِتابِ اللهِ عِنْدَ الشُّبُهاتِ.",
"source": "عيون الحكم والمواعظ"
},
{
"text": "رَدْعُ النَّفْسِ وَ جِهادُها عَنْ أَهْوِيَتِها يَرْفَعُ الدَّرَجاتِ وَ يُضاعِفُ الْحَسَناتِ.",
"source": "عيون الحكم والمواعظ"
},
{
"text": "رَضِيَ بِالذُّلِّ مَنْ كَشَفَ ضُرَّهُ لِغَيرِه.",
"source": "عيون الحكم والمواعظ"
},
{
"text": "رَحْمَةُ الضُّعَفاءِ تَسْتَنْزِلُ الرَّحْمَةَ.",
"source": "عيون الحكم والمواعظ"
},
{
"text": "رَضِيَ بِالْحِرْمانِ طالِبُ الرِّزْقِ مِنَ اللِّئامِ.",
"source": "عيون الحكم والمواعظ"
},
{
"text": "رَغْبَةُ الْعاقِلِ فِي الْحِكْمَةِ وَ هِمَّةُ الْجاهِلِ فِي الْحَماقَةِ.",
"source": "عيون الحكم والمواعظ"
},
{
"text": "رُكُوبُ الْمَعاطِبِ عُنْوانُ الْحَماقَةِ.",
"source": "عيون الحكم والمواعظ"
},
{
"text": "رَأْيُ الرَّجُل ميزانُ عَقْلِه.",
"source": "عيون الحكم والمواعظ"
},
{
"text": "رِزْقُ الرَّجُلِ مُقَدَّرٌ كَتَقْديرِ أَجَلِه.",
"source": "عيون الحكم والمواعظ"
},
{
"text": "رَحْمَةُ مَنْ لا يَرْحَمُ تَمْنَعُ الرَّحْمَةَ وَ اسْتِبقاءُ مَنْ لا يُبْقي يُهْلِكُ الْاُمَّةَ.",
"source": "عيون الحكم والمواعظ"
},
{
"text": "رَسُولُ الرَّجُلِ تَرْجُمانُ عَقْلِه وَ كِتابُهُ أَبْلَغُ مِنْ نُطْقِه.",
"source": "عيون الحكم والمواعظ"
},
{
"text": "رُوَيْداً يُسْفِرُ الظَّلامَ كَأَنْ قَدْ وَرَدَتِ الْأَظْعانُ يُوشِكُ مَنْ أَسْرَعَ أَنْ يَلْحَقَ.",
"source": "عيون الحكم والمواعظ"
},
{
"text": "راكِبُ الْمَعْصِيَةِ مَثْواهُ النّارُ.",
"source": "عيون الحكم والمواعظ"
},
{
"text": "راكِبُ الظُّلمِ يُدْرِكُهُ الْبَوارُ.",
"source": "عيون الحكم والمواعظ"
},
{
"text": "راكِبُ الطّاعَةِ مَقيلُهُ الْجَنَّةُ.",
"source": "عيون الحكم والمواعظ"
},
{
"text": "راكِبُ الْعَجَلِ مُشْفٍ عَلى الْكَبْوَةِ.",
"source": "عيون الحكم والمواعظ"
},
{
"text": "رُدَّ الْحَجَرَ مِنْ حَيْثُ جاءَ|كَ فَإِنَّهُ لا يُدْفَعُ الشَّرُّ إِلّا بِالشَّرِّ.",
"source": "عيون الحكم والمواعظ"
},
{
"text": "رَسُولُ اللهِ صلّى الله عليه و آله تَرْجُمانُ الْحَقِّ وَ السَّفيرُ بَينَ الْخَلائِقِ.",
"source": "عيون الحكم والمواعظ"
},
{
"text": "رَفاهِيَّةُ الْعَيْشِ فِي الْأَمْنِ.",
"source": "عيون الحكم والمواعظ"
},
{
"text": "رَزانَةُ الْعَقْلِ تُخْتَبَرُ فِي الْفَرَحِ وَ الْحُزْنِ.",
"source": "عيون الحكم والمواعظ"
}
]
}