{
"title": "الهوى",
"type": "text",
"data": [
{
"text": "يَا أَيُّهَا الَّذِينَ آمَنُواْ كُونُواْ قَوَّامِينَ بِالْقِسْطِ شُهَدَاء لِلّهِ وَلَوْ عَلَى أَنفُسِكُمْ أَوِ الْوَالِدَيْنِ وَالأَقْرَبِينَ إِن يَكُنْ غَنِيّاً أَوْ فَقَيراً فَاللّهُ أَوْلَى بِهِمَا فَلاَ تَتَّبِعُواْ الْهَوَى أَن تَعْدِلُواْ وَإِن تَلْوُواْ أَوْ تُعْرِضُواْ فَإِنَّ اللّهَ كَانَ بِمَا تَعْمَلُونَ خَبِيراً ",
"source": "النساء 135"
},
{
"text": "فَإِن لَّمْ يَسْتَجِيبُوا لَكَ فَاعْلَمْ أَنَّمَا يَتَّبِعُونَ أَهْوَاءهُمْ وَمَنْ أَضَلُّ مِمَّنِ اتَّبَعَ هَوَاهُ بِغَيْرِ هُدًى مِّنَ اللَّهِ إِنَّ اللَّهَ لَا يَهْدِي الْقَوْمَ الظَّالِمِينَ ",
"source": "القصص 50"
},
{
"text": "بَلِ اتَّبَعَ الَّذِينَ ظَلَمُوا أَهْوَاءهُم بِغَيْرِ عِلْمٍ فَمَن يَهْدِي مَنْ أَضَلَّ اللَّهُ وَمَا لَهُم مِّن نَّاصِرِينَ ",
"source": "الروم 29"
},
{
"text": "يَا دَاوُودُ إِنَّا جَعَلْنَاكَ خَلِيفَةً فِي الْأَرْضِ فَاحْكُم بَيْنَ النَّاسِ بِالْحَقِّ وَلَا تَتَّبِعِ الْهَوَى فَيُضِلَّكَ عَن سَبِيلِ اللَّهِ إِنَّ الَّذِينَ يَضِلُّونَ عَن سَبِيلِ اللَّهِ لَهُمْ عَذَابٌ شَدِيدٌ بِمَا نَسُوا يَوْمَ الْحِسَابِ ",
"source": "ص 26"
}
]
}